Workbook

Sheet Instructions
B2: Sales Performance Dashboard
B3: A complete Excel reporting project: raw data, lookup tables, analysis layer and an interactive dashboard.
B5: Sheet | C5: What it does
B6: Dashboard | C6: KPIs, insights and charts. Use the region dropdown (yellow cell) to filter the monthly, product and category views.
B7: Analysis | C7: All the SUMIFS / COUNTIFS summary tables that feed the dashboard charts.
B8: Data | C8: 400 sample orders. Blue columns are inputs; black columns are formulas (lookups, revenue, cost, profit).
B9: Lists | C9: Product prices and costs, salespeople with region and annual target, and the reporting start month.
B11: How to use
B12: 1. Add new orders at the bottom of the Data sheet: fill the blue columns A-F, then copy the formulas in G-N down (summary ranges cover rows 2-2000).
B13: 2. Change prices, costs, targets or the start month on the Lists sheet; everything recalculates.
B14: 3. Pick a region on the Dashboard (cell C4) to filter the KPIs and charts. 'All' shows the whole business.
B15: 4. Colour code: blue text = input you can change, black = formula, green = link from another sheet, yellow fill = control cell.
B17: Assumptions & notes
B18: All orders, prices, costs and targets are generated sample data for demonstration (not real figures). Replace them with your own.
B19: Revenue = Qty x Unit Price x (1 - Discount). Cost = Qty x Unit Cost. Profit = Revenue - Cost. Currency shown in $.
B20: Targets on the Lists sheet are annual per salesperson and are compared to revenue over the 12 months shown.

Sheet Dashboard
B1: Sales Performance Dashboard
B2: ="12 months from "&TEXT(Lists!B2,"mmm yyyy")&" | Sample data" -> 12 months from Oct 2025 | Sample data
B4: Region | C4: All | D4: <- pick All, North, South, East or West
B6: Revenue | D6: Profit | F6: Profit margin | H6: Orders | J6: Avg order value | L6: Units sold
B7: =Analysis!C18 -> 778347.5 | D7: =Analysis!D18 -> 278750.5 | F7: =Analysis!E18 -> 0.35813117 | H7: =Analysis!B18 -> 400 | J7: =IF(Analysis!B18=0,0,Analysis!C18/Analysis!B18) -> 1945.8688 | L7: =SUM(Analysis!B23:B30) -> 3163
B9: Key insights
B10: ="Best month: "&TEXT(INDEX(Analysis!A6:A17,MATCH(MAX(Analysis!C6:C17),Analysis!C6:C17,0)),"mmm yyyy")&" ("&TEXT(MAX(Analysis!C6:C17),"$#,##0")&" revenue)" -> Best month: Dec 2025 ($83,738 revenue)
B11: ="Top product: "&INDEX(Analysis!A23:A30,MATCH(MAX(Analysis!C23:C30),Analysis!C23:C30,0))&" ("&TEXT(MAX(Analysis!C23:C30),"$#,##0")&")" -> Top product: Laptop Air ($186,080)
B12: ="Highest-margin product: "&INDEX(Analysis!A23:A30,MATCH(MAX(Analysis!E23:E30),Analysis!E23:E30,0))&" ("&TEXT(MAX(Analysis!E23:E30),"0.0%")&")" -> Highest-margin product: Mouse (50.4%)
B13: ="Top region (all regions): "&INDEX(Analysis!G6:G9,MATCH(MAX(Analysis!H6:H9),Analysis!H6:H9,0))&" ("&TEXT(MAX(Analysis!K6:K9),"0%")&" of revenue)" -> Top region (all regions): East (27% of revenue)
B14: ="Salespeople at or above target: "&COUNTIF(Analysis!E35:E42,">=1")&" of "&COUNTA(Analysis!A35:A42) -> Salespeople at or above target: 3 of 8

Sheet Analysis
A1: Analysis tables
A2: Region filter (from Dashboard) | B2: =Dashboard!$C$4 -> All | C2: Criteria used | D2: =IF(B2="All","*",B2) -> *
A4: Monthly trend (filtered by region) | G4: By region (all regions)
A5: Month | B5: Orders | C5: Revenue | D5: Profit | E5: Margin | G5: Region | H5: Revenue | I5: Profit | J5: Margin | K5: Share
A6: =Lists!$B$2 -> 45931 | B6: =COUNTIFS(Data!$N$2:$N$2000,A6,Data!$G$2:$G$2000,$D$2) -> 28 | C6: =SUMIFS(Data!$K$2:$K$2000,Data!$N$2:$N$2000,A6,Data!$G$2:$G$2000,$D$2) -> 48234 | D6: =SUMIFS(Data!$M$2:$M$2000,Data!$N$2:$N$2000,A6,Data!$G$2:$G$2000,$D$2) -> 17386 | E6: =IF(C6=0,0,D6/C6) -> 0.36045113 | G6: =Lists!J5 -> North | H6: =SUMIFS(Data!$K$2:$K$2000,Data!$G$2:$G$2000,G6) -> 203546.5 | I6: =SUMIFS(Data!$M$2:$M$2000,Data!$G$2:$G$2000,G6) -> 73868.5 | J6: =IF(H6=0,0,I6/H6) -> 0.36290725 | K6: =IF($H$10=0,0,H6/$H$10) -> 0.26151109
A7: =EDATE(A6,1) -> 45962 | B7: =COUNTIFS(Data!$N$2:$N$2000,A7,Data!$G$2:$G$2000,$D$2) -> 34 | C7: =SUMIFS(Data!$K$2:$K$2000,Data!$N$2:$N$2000,A7,Data!$G$2:$G$2000,$D$2) -> 59667.5 | D7: =SUMIFS(Data!$M$2:$M$2000,Data!$N$2:$N$2000,A7,Data!$G$2:$G$2000,$D$2) -> 21500.5 | E7: =IF(C7=0,0,D7/C7) -> 0.36033854 | G7: =Lists!J6 -> South | H7: =SUMIFS(Data!$K$2:$K$2000,Data!$G$2:$G$2000,G7) -> 165410 | I7: =SUMIFS(Data!$M$2:$M$2000,Data!$G$2:$G$2000,G7) -> 56834 | J7: =IF(H7=0,0,I7/H7) -> 0.3435947 | K7: =IF($H$10=0,0,H7/$H$10) -> 0.21251433
A8: =EDATE(A7,1) -> 45992 | B8: =COUNTIFS(Data!$N$2:$N$2000,A8,Data!$G$2:$G$2000,$D$2) -> 49 | C8: =SUMIFS(Data!$K$2:$K$2000,Data!$N$2:$N$2000,A8,Data!$G$2:$G$2000,$D$2) -> 83737.5 | D8: =SUMIFS(Data!$M$2:$M$2000,Data!$N$2:$N$2000,A8,Data!$G$2:$G$2000,$D$2) -> 31916.5 | E8: =IF(C8=0,0,D8/C8) -> 0.38114943 | G8: =Lists!J7 -> East | H8: =SUMIFS(Data!$K$2:$K$2000,Data!$G$2:$G$2000,G8) -> 209896 | I8: =SUMIFS(Data!$M$2:$M$2000,Data!$G$2:$G$2000,G8) -> 76358 | J8: =IF(H8=0,0,I8/H8) -> 0.36378969 | K8: =IF($H$10=0,0,H8/$H$10) -> 0.26966875
A9: =EDATE(A8,1) -> 46023 | B9: =COUNTIFS(Data!$N$2:$N$2000,A9,Data!$G$2:$G$2000,$D$2) -> 28 | C9: =SUMIFS(Data!$K$2:$K$2000,Data!$N$2:$N$2000,A9,Data!$G$2:$G$2000,$D$2) -> 71169 | D9: =SUMIFS(Data!$M$2:$M$2000,Data!$N$2:$N$2000,A9,Data!$G$2:$G$2000,$D$2) -> 22164 | E9: =IF(C9=0,0,D9/C9) -> 0.31142773 | G9: =Lists!J8 -> West | H9: =SUMIFS(Data!$K$2:$K$2000,Data!$G$2:$G$2000,G9) -> 199495 | I9: =SUMIFS(Data!$M$2:$M$2000,Data!$G$2:$G$2000,G9) -> 71690 | J9: =IF(H9=0,0,I9/H9) -> 0.35935738 | K9: =IF($H$10=0,0,H9/$H$10) -> 0.25630583
A10: =EDATE(A9,1) -> 46054 | B10: =COUNTIFS(Data!$N$2:$N$2000,A10,Data!$G$2:$G$2000,$D$2) -> 23 | C10: =SUMIFS(Data!$K$2:$K$2000,Data!$N$2:$N$2000,A10,Data!$G$2:$G$2000,$D$2) -> 51020.5 | D10: =SUMIFS(Data!$M$2:$M$2000,Data!$N$2:$N$2000,A10,Data!$G$2:$G$2000,$D$2) -> 16264.5 | E10: =IF(C10=0,0,D10/C10) -> 0.31878363 | G10: Total | H10: =SUM(H6:H9) -> 778347.5 | I10: =SUM(I6:I9) -> 278750.5 | J10: =IF(H10=0,0,I10/H10) -> 0.35813117 | K10: =SUM(K6:K9) -> 1
A11: =EDATE(A10,1) -> 46082 | B11: =COUNTIFS(Data!$N$2:$N$2000,A11,Data!$G$2:$G$2000,$D$2) -> 27 | C11: =SUMIFS(Data!$K$2:$K$2000,Data!$N$2:$N$2000,A11,Data!$G$2:$G$2000,$D$2) -> 58207 | D11: =SUMIFS(Data!$M$2:$M$2000,Data!$N$2:$N$2000,A11,Data!$G$2:$G$2000,$D$2) -> 19804 | E11: =IF(C11=0,0,D11/C11) -> 0.34023399
A12: =EDATE(A11,1) -> 46113 | B12: =COUNTIFS(Data!$N$2:$N$2000,A12,Data!$G$2:$G$2000,$D$2) -> 30 | C12: =SUMIFS(Data!$K$2:$K$2000,Data!$N$2:$N$2000,A12,Data!$G$2:$G$2000,$D$2) -> 51774 | D12: =SUMIFS(Data!$M$2:$M$2000,Data!$N$2:$N$2000,A12,Data!$G$2:$G$2000,$D$2) -> 17898 | E12: =IF(C12=0,0,D12/C12) -> 0.34569475
A13: =EDATE(A12,1) -> 46143 | B13: =COUNTIFS(Data!$N$2:$N$2000,A13,Data!$G$2:$G$2000,$D$2) -> 31 | C13: =SUMIFS(Data!$K$2:$K$2000,Data!$N$2:$N$2000,A13,Data!$G$2:$G$2000,$D$2) -> 75756 | D13: =SUMIFS(Data!$M$2:$M$2000,Data!$N$2:$N$2000,A13,Data!$G$2:$G$2000,$D$2) -> 25964 | E13: =IF(C13=0,0,D13/C13) -> 0.34273193
A14: =EDATE(A13,1) -> 46174 | B14: =COUNTIFS(Data!$N$2:$N$2000,A14,Data!$G$2:$G$2000,$D$2) -> 35 | C14: =SUMIFS(Data!$K$2:$K$2000,Data!$N$2:$N$2000,A14,Data!$G$2:$G$2000,$D$2) -> 70280 | D14: =SUMIFS(Data!$M$2:$M$2000,Data!$N$2:$N$2000,A14,Data!$G$2:$G$2000,$D$2) -> 25675 | E14: =IF(C14=0,0,D14/C14) -> 0.36532442
A15: =EDATE(A14,1) -> 46204 | B15: =COUNTIFS(Data!$N$2:$N$2000,A15,Data!$G$2:$G$2000,$D$2) -> 41 | C15: =SUMIFS(Data!$K$2:$K$2000,Data!$N$2:$N$2000,A15,Data!$G$2:$G$2000,$D$2) -> 77898.5 | D15: =SUMIFS(Data!$M$2:$M$2000,Data!$N$2:$N$2000,A15,Data!$G$2:$G$2000,$D$2) -> 29451.5 | E15: =IF(C15=0,0,D15/C15) -> 0.37807532
A16: =EDATE(A15,1) -> 46235 | B16: =COUNTIFS(Data!$N$2:$N$2000,A16,Data!$G$2:$G$2000,$D$2) -> 39 | C16: =SUMIFS(Data!$K$2:$K$2000,Data!$N$2:$N$2000,A16,Data!$G$2:$G$2000,$D$2) -> 73205.5 | D16: =SUMIFS(Data!$M$2:$M$2000,Data!$N$2:$N$2000,A16,Data!$G$2:$G$2000,$D$2) -> 28920.5 | E16: =IF(C16=0,0,D16/C16) -> 0.39505911
A17: =EDATE(A16,1) -> 46266 | B17: =COUNTIFS(Data!$N$2:$N$2000,A17,Data!$G$2:$G$2000,$D$2) -> 35 | C17: =SUMIFS(Data!$K$2:$K$2000,Data!$N$2:$N$2000,A17,Data!$G$2:$G$2000,$D$2) -> 57398 | D17: =SUMIFS(Data!$M$2:$M$2000,Data!$N$2:$N$2000,A17,Data!$G$2:$G$2000,$D$2) -> 21806 | E17: =IF(C17=0,0,D17/C17) -> 0.37990871
A18: Total | B18: =SUM(B6:B17) -> 400 | C18: =SUM(C6:C17) -> 778347.5 | D18: =SUM(D6:D17) -> 278750.5 | E18: =IF(C18=0,0,D18/C18) -> 0.35813117
A21: By product (filtered by region) | G21: By category (filtered by region)
A22: Product | B22: Units | C22: Revenue | D22: Profit | E22: Margin | G22: Category | H22: Revenue | I22: Profit | J22: Margin
A23: =Lists!A5 -> Laptop Pro | B23: =SUMIFS(Data!$E$2:$E$2000,Data!$D$2:$D$2000,A23,Data!$G$2:$G$2000,$D$2) -> 66 | C23: =SUMIFS(Data!$K$2:$K$2000,Data!$D$2:$D$2000,A23,Data!$G$2:$G$2000,$D$2) -> 151800 | D23: =SUMIFS(Data!$M$2:$M$2000,Data!$D$2:$D$2000,A23,Data!$G$2:$G$2000,$D$2) -> 42900 | E23: =IF(C23=0,0,D23/C23) -> 0.2826087 | G23: Computers | H23: =SUMIFS(Data!$K$2:$K$2000,Data!$H$2:$H$2000,G23,Data!$G$2:$G$2000,$D$2) -> 337880 | I23: =SUMIFS(Data!$M$2:$M$2000,Data!$H$2:$H$2000,G23,Data!$G$2:$G$2000,$D$2) -> 94780 | J23: =IF(H23=0,0,I23/H23) -> 0.28051379
A24: =Lists!A6 -> Laptop Air | B24: =SUMIFS(Data!$E$2:$E$2000,Data!$D$2:$D$2000,A24,Data!$G$2:$G$2000,$D$2) -> 122 | C24: =SUMIFS(Data!$K$2:$K$2000,Data!$D$2:$D$2000,A24,Data!$G$2:$G$2000,$D$2) -> 186080 | D24: =SUMIFS(Data!$M$2:$M$2000,Data!$D$2:$D$2000,A24,Data!$G$2:$G$2000,$D$2) -> 51880 | E24: =IF(C24=0,0,D24/C24) -> 0.27880482 | G24: Displays | H24: =SUMIFS(Data!$K$2:$K$2000,Data!$H$2:$H$2000,G24,Data!$G$2:$G$2000,$D$2) -> 108966 | I24: =SUMIFS(Data!$M$2:$M$2000,Data!$H$2:$H$2000,G24,Data!$G$2:$G$2000,$D$2) -> 33826 | J24: =IF(H24=0,0,I24/H24) -> 0.31042711
A25: =Lists!A7 -> Monitor 27" | B25: =SUMIFS(Data!$E$2:$E$2000,Data!$D$2:$D$2000,A25,Data!$G$2:$G$2000,$D$2) -> 221 | C25: =SUMIFS(Data!$K$2:$K$2000,Data!$D$2:$D$2000,A25,Data!$G$2:$G$2000,$D$2) -> 108966 | D25: =SUMIFS(Data!$M$2:$M$2000,Data!$D$2:$D$2000,A25,Data!$G$2:$G$2000,$D$2) -> 33826 | E25: =IF(C25=0,0,D25/C25) -> 0.31042711 | G25: Accessories | H25: =SUMIFS(Data!$K$2:$K$2000,Data!$H$2:$H$2000,G25,Data!$G$2:$G$2000,$D$2) -> 229968 | I25: =SUMIFS(Data!$M$2:$M$2000,Data!$H$2:$H$2000,G25,Data!$G$2:$G$2000,$D$2) -> 106186 | J25: =IF(H25=0,0,I25/H25) -> 0.4617425
A26: =Lists!A8 -> Docking Station | B26: =SUMIFS(Data!$E$2:$E$2000,Data!$D$2:$D$2000,A26,Data!$G$2:$G$2000,$D$2) -> 182 | C26: =SUMIFS(Data!$K$2:$K$2000,Data!$D$2:$D$2000,A26,Data!$G$2:$G$2000,$D$2) -> 45162 | D26: =SUMIFS(Data!$M$2:$M$2000,Data!$D$2:$D$2000,A26,Data!$G$2:$G$2000,$D$2) -> 17862 | E26: =IF(C26=0,0,D26/C26) -> 0.3955095 | G26: Audio | H26: =SUMIFS(Data!$K$2:$K$2000,Data!$H$2:$H$2000,G26,Data!$G$2:$G$2000,$D$2) -> 101533.5 | I26: =SUMIFS(Data!$M$2:$M$2000,Data!$H$2:$H$2000,G26,Data!$G$2:$G$2000,$D$2) -> 43958.5 | J26: =IF(H26=0,0,I26/H26) -> 0.43294578
A27: =Lists!A9 -> Keyboard | B27: =SUMIFS(Data!$E$2:$E$2000,Data!$D$2:$D$2000,A27,Data!$G$2:$G$2000,$D$2) -> 950 | C27: =SUMIFS(Data!$K$2:$K$2000,Data!$D$2:$D$2000,A27,Data!$G$2:$G$2000,$D$2) -> 108978 | D27: =SUMIFS(Data!$M$2:$M$2000,Data!$D$2:$D$2000,A27,Data!$G$2:$G$2000,$D$2) -> 50078 | E27: =IF(C27=0,0,D27/C27) -> 0.45952394
A28: =Lists!A10 -> Mouse | B28: =SUMIFS(Data!$E$2:$E$2000,Data!$D$2:$D$2000,A28,Data!$G$2:$G$2000,$D$2) -> 989 | C28: =SUMIFS(Data!$K$2:$K$2000,Data!$D$2:$D$2000,A28,Data!$G$2:$G$2000,$D$2) -> 75828 | D28: =SUMIFS(Data!$M$2:$M$2000,Data!$D$2:$D$2000,A28,Data!$G$2:$G$2000,$D$2) -> 38246 | E28: =IF(C28=0,0,D28/C28) -> 0.50437833
A29: =Lists!A11 -> Headset | B29: =SUMIFS(Data!$E$2:$E$2000,Data!$D$2:$D$2000,A29,Data!$G$2:$G$2000,$D$2) -> 379 | C29: =SUMIFS(Data!$K$2:$K$2000,Data!$D$2:$D$2000,A29,Data!$G$2:$G$2000,$D$2) -> 67877.5 | D29: =SUMIFS(Data!$M$2:$M$2000,Data!$D$2:$D$2000,A29,Data!$G$2:$G$2000,$D$2) -> 28082.5 | E29: =IF(C29=0,0,D29/C29) -> 0.41372325
A30: =Lists!A12 -> Webcam | B30: =SUMIFS(Data!$E$2:$E$2000,Data!$D$2:$D$2000,A30,Data!$G$2:$G$2000,$D$2) -> 254 | C30: =SUMIFS(Data!$K$2:$K$2000,Data!$D$2:$D$2000,A30,Data!$G$2:$G$2000,$D$2) -> 33656 | D30: =SUMIFS(Data!$M$2:$M$2000,Data!$D$2:$D$2000,A30,Data!$G$2:$G$2000,$D$2) -> 15876 | E30: =IF(C30=0,0,D30/C30) -> 0.47171381
A33: Salesperson vs annual target (all regions)
A34: Salesperson | B34: Region | C34: Revenue | D34: Target | E34: Attainment
A35: =Lists!F5 -> Aisha Khan | B35: =Lists!G5 -> North | C35: =SUMIFS(Data!$K$2:$K$2000,Data!$C$2:$C$2000,A35) -> 87518.5 | D35: =Lists!H5 -> 105000 | E35: =IF(D35=0,0,C35/D35) -> 0.83350952
A36: =Lists!F6 -> Ben Carter | B36: =Lists!G6 -> North | C36: =SUMIFS(Data!$K$2:$K$2000,Data!$C$2:$C$2000,A36) -> 116028 | D36: =Lists!H6 -> 90000 | E36: =IF(D36=0,0,C36/D36) -> 1.2892
A37: =Lists!F7 -> Chloe Nguyen | B37: =Lists!G7 -> South | C37: =SUMIFS(Data!$K$2:$K$2000,Data!$C$2:$C$2000,A37) -> 92489.5 | D37: =Lists!H7 -> 100000 | E37: =IF(D37=0,0,C37/D37) -> 0.924895
A38: =Lists!F8 -> Daniel Ortiz | B38: =Lists!G8 -> South | C38: =SUMIFS(Data!$K$2:$K$2000,Data!$C$2:$C$2000,A38) -> 72920.5 | D38: =Lists!H8 -> 85000 | E38: =IF(D38=0,0,C38/D38) -> 0.85788824
A39: =Lists!F9 -> Emma Walsh | B39: =Lists!G9 -> East | C39: =SUMIFS(Data!$K$2:$K$2000,Data!$C$2:$C$2000,A39) -> 108616.5 | D39: =Lists!H9 -> 110000 | E39: =IF(D39=0,0,C39/D39) -> 0.98742273
A40: =Lists!F10 -> Farid Haddad | B40: =Lists!G10 -> East | C40: =SUMIFS(Data!$K$2:$K$2000,Data!$C$2:$C$2000,A40) -> 101279.5 | D40: =Lists!H10 -> 95000 | E40: =IF(D40=0,0,C40/D40) -> 1.0661
A41: =Lists!F11 -> Grace Liu | B41: =Lists!G11 -> West | C41: =SUMIFS(Data!$K$2:$K$2000,Data!$C$2:$C$2000,A41) -> 111719 | D41: =Lists!H11 -> 98000 | E41: =IF(D41=0,0,C41/D41) -> 1.1399898
A42: =Lists!F12 -> Hugo Martin | B42: =Lists!G12 -> West | C42: =SUMIFS(Data!$K$2:$K$2000,Data!$C$2:$C$2000,A42) -> 87776 | D42: =Lists!H12 -> 88000 | E42: =IF(D42=0,0,C42/D42) -> 0.99745455

Sheet Data
A1: Order ID | B1: Date | C1: Salesperson | D1: Product | E1: Qty | F1: Discount % | G1: Region | H1: Category | I1: Unit Price | J1: Unit Cost | K1: Revenue | L1: Cost | M1: Profit | N1: Month
A2: ORD-0001 | B2: 45931 | C2: Daniel Ortiz | D2: Laptop Air | E2: 2 | F2: 0.05 | G2: =INDEX(Lists!$G$5:$G$12,MATCH(C2,Lists!$F$5:$F$12,0)) -> South | H2: =INDEX(Lists!$B$5:$B$12,MATCH(D2,Lists!$A$5:$A$12,0)) -> Computers | I2: =INDEX(Lists!$C$5:$C$12,MATCH(D2,Lists!$A$5:$A$12,0)) -> 1600 | J2: =INDEX(Lists!$D$5:$D$12,MATCH(D2,Lists!$A$5:$A$12,0)) -> 1100 | K2: =E2*I2*(1-F2) -> 3040 | L2: =E2*J2 -> 2200 | M2: =K2-L2 -> 840 | N2: =DATE(YEAR(B2),MONTH(B2),1) -> 45931
A3: ORD-0002 | B3: 45931 | C3: Farid Haddad | D3: Docking Station | E3: 6 | F3: 0.05 | G3: =INDEX(Lists!$G$5:$G$12,MATCH(C3,Lists!$F$5:$F$12,0)) -> East | H3: =INDEX(Lists!$B$5:$B$12,MATCH(D3,Lists!$A$5:$A$12,0)) -> Accessories | I3: =INDEX(Lists!$C$5:$C$12,MATCH(D3,Lists!$A$5:$A$12,0)) -> 260 | J3: =INDEX(Lists!$D$5:$D$12,MATCH(D3,Lists!$A$5:$A$12,0)) -> 150 | K3: =E3*I3*(1-F3) -> 1482 | L3: =E3*J3 -> 900 | M3: =K3-L3 -> 582 | N3: =DATE(YEAR(B3),MONTH(B3),1) -> 45931
A4: ORD-0003 | B4: 45933 | C4: Farid Haddad | D4: Keyboard | E4: 15 | F4: 0 | G4: =INDEX(Lists!$G$5:$G$12,MATCH(C4,Lists!$F$5:$F$12,0)) -> East | H4: =INDEX(Lists!$B$5:$B$12,MATCH(D4,Lists!$A$5:$A$12,0)) -> Accessories | I4: =INDEX(Lists!$C$5:$C$12,MATCH(D4,Lists!$A$5:$A$12,0)) -> 120 | J4: =INDEX(Lists!$D$5:$D$12,MATCH(D4,Lists!$A$5:$A$12,0)) -> 62 | K4: =E4*I4*(1-F4) -> 1800 | L4: =E4*J4 -> 930 | M4: =K4-L4 -> 870 | N4: =DATE(YEAR(B4),MONTH(B4),1) -> 45931
A5: ORD-0004 | B5: 45933 | C5: Emma Walsh | D5: Monitor 27" | E5: 2 | F5: 0 | G5: =INDEX(Lists!$G$5:$G$12,MATCH(C5,Lists!$F$5:$F$12,0)) -> East | H5: =INDEX(Lists!$B$5:$B$12,MATCH(D5,Lists!$A$5:$A$12,0)) -> Displays | I5: =INDEX(Lists!$C$5:$C$12,MATCH(D5,Lists!$A$5:$A$12,0)) -> 520 | J5: =INDEX(Lists!$D$5:$D$12,MATCH(D5,Lists!$A$5:$A$12,0)) -> 340 | K5: =E5*I5*(1-F5) -> 1040 | L5: =E5*J5 -> 680 | M5: =K5-L5 -> 360 | N5: =DATE(YEAR(B5),MONTH(B5),1) -> 45931
A6: ORD-0005 | B6: 45933 | C6: Farid Haddad | D6: Mouse | E6: 18 | F6: 0 | G6: =INDEX(Lists!$G$5:$G$12,MATCH(C6,Lists!$F$5:$F$12,0)) -> East | H6: =INDEX(Lists!$B$5:$B$12,MATCH(D6,Lists!$A$5:$A$12,0)) -> Accessories | I6: =INDEX(Lists!$C$5:$C$12,MATCH(D6,Lists!$A$5:$A$12,0)) -> 80 | J6: =INDEX(Lists!$D$5:$D$12,MATCH(D6,Lists!$A$5:$A$12,0)) -> 38 | K6: =E6*I6*(1-F6) -> 1440 | L6: =E6*J6 -> 684 | M6: =K6-L6 -> 756 | N6: =DATE(YEAR(B6),MONTH(B6),1) -> 45931
A7: ORD-0006 | B7: 45933 | C7: Chloe Nguyen | D7: Webcam | E7: 7 | F7: 0 | G7: =INDEX(Lists!$G$5:$G$12,MATCH(C7,Lists!$F$5:$F$12,0)) -> South | H7: =INDEX(Lists!$B$5:$B$12,MATCH(D7,Lists!$A$5:$A$12,0)) -> Audio | I7: =INDEX(Lists!$C$5:$C$12,MATCH(D7,Lists!$A$5:$A$12,0)) -> 140 | J7: =INDEX(Lists!$D$5:$D$12,MATCH(D7,Lists!$A$5:$A$12,0)) -> 70 | K7: =E7*I7*(1-F7) -> 980 | L7: =E7*J7 -> 490 | M7: =K7-L7 -> 490 | N7: =DATE(YEAR(B7),MONTH(B7),1) -> 45931
A8: ORD-0007 | B8: 45937 | C8: Emma Walsh | D8: Mouse | E8: 19 | F8: 0.1 | G8: =INDEX(Lists!$G$5:$G$12,MATCH(C8,Lists!$F$5:$F$12,0)) -> East | H8: =INDEX(Lists!$B$5:$B$12,MATCH(D8,Lists!$A$5:$A$12,0)) -> Accessories | I8: =INDEX(Lists!$C$5:$C$12,MATCH(D8,Lists!$A$5:$A$12,0)) -> 80 | J8: =INDEX(Lists!$D$5:$D$12,MATCH(D8,Lists!$A$5:$A$12,0)) -> 38 | K8: =E8*I8*(1-F8) -> 1368 | L8: =E8*J8 -> 722 | M8: =K8-L8 -> 646 | N8: =DATE(YEAR(B8),MONTH(B8),1) -> 45931
A9: ORD-0008 | B9: 45937 | C9: Emma Walsh | D9: Webcam | E9: 7 | F9: 0 | G9: =INDEX(Lists!$G$5:$G$12,MATCH(C9,Lists!$F$5:$F$12,0)) -> East | H9: =INDEX(Lists!$B$5:$B$12,MATCH(D9,Lists!$A$5:$A$12,0)) -> Audio | I9: =INDEX(Lists!$C$5:$C$12,MATCH(D9,Lists!$A$5:$A$12,0)) -> 140 | J9: =INDEX(Lists!$D$5:$D$12,MATCH(D9,Lists!$A$5:$A$12,0)) -> 70 | K9: =E9*I9*(1-F9) -> 980 | L9: =E9*J9 -> 490 | M9: =K9-L9 -> 490 | N9: =DATE(YEAR(B9),MONTH(B9),1) -> 45931
A10: ORD-0009 | B10: 45938 | C10: Farid Haddad | D10: Docking Station | E10: 5 | F10: 0 | G10: =INDEX(Lists!$G$5:$G$12,MATCH(C10,Lists!$F$5:$F$12,0)) -> East | H10: =INDEX(Lists!$B$5:$B$12,MATCH(D10,Lists!$A$5:$A$12,0)) -> Accessories | I10: =INDEX(Lists!$C$5:$C$12,MATCH(D10,Lists!$A$5:$A$12,0)) -> 260 | J10: =INDEX(Lists!$D$5:$D$12,MATCH(D10,Lists!$A$5:$A$12,0)) -> 150 | K10: =E10*I10*(1-F10) -> 1300 | L10: =E10*J10 -> 750 | M10: =K10-L10 -> 550 | N10: =DATE(YEAR(B10),MONTH(B10),1) -> 45931
A11: ORD-0010 | B11: 45940 | C11: Chloe Nguyen | D11: Laptop Pro | E11: 1 | F11: 0 | G11: =INDEX(Lists!$G$5:$G$12,MATCH(C11,Lists!$F$5:$F$12,0)) -> South | H11: =INDEX(Lists!$B$5:$B$12,MATCH(D11,Lists!$A$5:$A$12,0)) -> Computers | I11: =INDEX(Lists!$C$5:$C$12,MATCH(D11,Lists!$A$5:$A$12,0)) -> 2400 | J11: =INDEX(Lists!$D$5:$D$12,MATCH(D11,Lists!$A$5:$A$12,0)) -> 1650 | K11: =E11*I11*(1-F11) -> 2400 | L11: =E11*J11 -> 1650 | M11: =K11-L11 -> 750 | N11: =DATE(YEAR(B11),MONTH(B11),1) -> 45931
A12: ORD-0011 | B12: 45940 | C12: Emma Walsh | D12: Webcam | E12: 5 | F12: 0.1 | G12: =INDEX(Lists!$G$5:$G$12,MATCH(C12,Lists!$F$5:$F$12,0)) -> East | H12: =INDEX(Lists!$B$5:$B$12,MATCH(D12,Lists!$A$5:$A$12,0)) -> Audio | I12: =INDEX(Lists!$C$5:$C$12,MATCH(D12,Lists!$A$5:$A$12,0)) -> 140 | J12: =INDEX(Lists!$D$5:$D$12,MATCH(D12,Lists!$A$5:$A$12,0)) -> 70 | K12: =E12*I12*(1-F12) -> 630 | L12: =E12*J12 -> 350 | M12: =K12-L12 -> 280 | N12: =DATE(YEAR(B12),MONTH(B12),1) -> 45931
A13: ORD-0012 | B13: 45940 | C13: Hugo Martin | D13: Mouse | E13: 1 | F13: 0 | G13: =INDEX(Lists!$G$5:$G$12,MATCH(C13,Lists!$F$5:$F$12,0)) -> West | H13: =INDEX(Lists!$B$5:$B$12,MATCH(D13,Lists!$A$5:$A$12,0)) -> Accessories | I13: =INDEX(Lists!$C$5:$C$12,MATCH(D13,Lists!$A$5:$A$12,0)) -> 80 | J13: =INDEX(Lists!$D$5:$D$12,MATCH(D13,Lists!$A$5:$A$12,0)) -> 38 | K13: =E13*I13*(1-F13) -> 80 | L13: =E13*J13 -> 38 | M13: =K13-L13 -> 42 | N13: =DATE(YEAR(B13),MONTH(B13),1) -> 45931
... A401: ORD-0400 | B401: 46295 | C401: Farid Haddad | D401: Keyboard | E401: 10 | F401: 0 | G401: =INDEX(Lists!$G$5:$G$12,MATCH(C401,Lists!$F$5:$F$12,0)) -> East | H401: =INDEX(Lists!$B$5:$B$12,MATCH(D401,Lists!$A$5:$A$12,0)) -> Accessories | I401: =INDEX(Lists!$C$5:$C$12,MATCH(D401,Lists!$A$5:$A$12,0)) -> 120 | J401: =INDEX(Lists!$D$5:$D$12,MATCH(D401,Lists!$A$5:$A$12,0)) -> 62 | K401: =E401*I401*(1-F401) -> 1200 | L401: =E401*J401 -> 620 | M401: =K401-L401 -> 580 | N401: =DATE(YEAR(B401),MONTH(B401),1) -> 46266

Sheet Lists
A1: Lookup tables & settings
A2: Reporting start month | B2: 45931 | C2: First of 12 months shown (input)
A4: Product | B4: Category | C4: Unit Price ($) | D4: Unit Cost ($) | F4: Salesperson | G4: Region | H4: Annual Target ($) | J4: Regions
A5: Laptop Pro | B5: Computers | C5: 2400 | D5: 1650 | F5: Aisha Khan | G5: North | H5: 105000 | J5: North
A6: Laptop Air | B6: Computers | C6: 1600 | D6: 1100 | F6: Ben Carter | G6: North | H6: 90000 | J6: South
A7: Monitor 27" | B7: Displays | C7: 520 | D7: 340 | F7: Chloe Nguyen | G7: South | H7: 100000 | J7: East
A8: Docking Station | B8: Accessories | C8: 260 | D8: 150 | F8: Daniel Ortiz | G8: South | H8: 85000 | J8: West
A9: Keyboard | B9: Accessories | C9: 120 | D9: 62 | F9: Emma Walsh | G9: East | H9: 110000
A10: Mouse | B10: Accessories | C10: 80 | D10: 38 | F10: Farid Haddad | G10: East | H10: 95000
A11: Headset | B11: Audio | C11: 190 | D11: 105 | F11: Grace Liu | G11: West | H11: 98000
A12: Webcam | B12: Audio | C12: 140 | D12: 70 | F12: Hugo Martin | G12: West | H12: 88000
